CHANGELOG.md
README.md
pyproject.toml
stack_overflow_watchman/__init__.py
stack_overflow_watchman/__main__.py
stack_overflow_watchman/clients/__init__.py
stack_overflow_watchman/clients/stack_overflow_wrapper.py
stack_overflow_watchman/exceptions.py
stack_overflow_watchman/loggers.py
stack_overflow_watchman/models/__init__.py
stack_overflow_watchman/models/models.py
stack_overflow_watchman/models/signature.py
stack_overflow_watchman/signature_updater.py
stack_overflow_watchman/stack_overflow_search.py
stack_overflow_watchman-1.0.0.dist-info/LICENSE
stack_overflow_watchman-1.0.0.dist-info/METADATA
stack_overflow_watchman-1.0.0.dist-info/WHEEL
stack_overflow_watchman-1.0.0.dist-info/entry_points.txt
stack_overflow_watchman-1.0.0.dist-info/RECORD
