Metadata-Version: 2.1
Name: stack-overflow-watchman
Version: 1.0.0
Summary: Detecting exposed secrets in Stack Overflow Enterprise for Teams
Home-page: https://papermtn.co.uk/category/tools/stack-overflow-watchman
License: GPL-3.0
Author: PaperMtn
Author-email: papermtn@protonmail.com
Requires-Python: >=3.12,<4.0
Classifier: License :: OSI Approved :: GNU General Public License v3 (GPLv3)
Classifier: Programming Language :: Python :: 3
Classifier: Programming Language :: Python :: 3.12
Requires-Dist: colorama (>=0.4.6,<0.5.0)
Requires-Dist: pylint (>=3.1.0,<4.0.0)
Requires-Dist: pyyaml (>=6.0.1,<7.0.0)
Requires-Dist: requests (>=2.31.0,<3.0.0)
Project-URL: Repository, https://github.com/PaperMtn/stack-overflow-watchman
